setup.py
pttcrawler/Article.py
pttcrawler/Board.py
pttcrawler/Global.py
pttcrawler/Logger.py
pttcrawler/Page.py
pttcrawler/WebRetriever.py
pttcrawler/__init__.py
pttcrawler.egg-info/PKG-INFO
pttcrawler.egg-info/SOURCES.txt
pttcrawler.egg-info/dependency_links.txt
pttcrawler.egg-info/requires.txt
pttcrawler.egg-info/top_level.txt
pttcrawler/stream/__init__.py
pttcrawler/stream/kafka_producer.py
pttcrawler/stream/monitor.py
pttcrawler/stream/receiver.py