Metadata-Version: 1.1
Name: pttcrawler
Version: 0.1.9
Summary: A stream crawler for ptt
Home-page: https://github.com/patrickyeh/python-pttcrawler
Author: Patrick Yeh
Author-email: vetom198@gmail.com
License: UNKNOWN
Platform: UNKNOWN
Classifier: Development Status :: 3 - Alpha
Classifier: Intended Audience :: Developers
Classifier: Operating System :: OS Independent
Classifier: Programming Language :: Python
Classifier: Programming Language :: Python :: 2
Classifier: Programming Language :: Python :: 2.6
Classifier: Programming Language :: Python :: 2.7
